dbpedia_ent/__init__.py
dbpedia_ent/bp/__init__.py
dbpedia_ent/bp/finder.py
dbpedia_ent/dmo/__init__.py
dbpedia_ent/dmo/ngram_exists.py
dbpedia_ent/dto/__init__.py
dbpedia_ent/dto/n1/__init__.py
dbpedia_ent/dto/n1/a/__init__.py
dbpedia_ent/dto/n1/a/finder_n1_a.py
dbpedia_ent/dto/n1/a/trie_a_.py
dbpedia_ent/dto/n1/a/trie_aa.py
dbpedia_ent/dto/n1/a/trie_ab.py
dbpedia_ent/dto/n1/a/trie_ac.py
dbpedia_ent/dto/n1/a/trie_ad.py
dbpedia_ent/dto/n1/a/trie_ae.py
dbpedia_ent/dto/n1/a/trie_af.py
dbpedia_ent/dto/n1/a/trie_ag.py
dbpedia_ent/dto/n1/a/trie_ah.py
dbpedia_ent/dto/n1/a/trie_ai.py
dbpedia_ent/dto/n1/a/trie_aj.py
dbpedia_ent/dto/n1/a/trie_ak.py
dbpedia_ent/dto/n1/a/trie_al.py
dbpedia_ent/dto/n1/a/trie_am.py
dbpedia_ent/dto/n1/a/trie_an.py
dbpedia_ent/dto/n1/a/trie_ao.py
dbpedia_ent/dto/n1/a/trie_ap.py
dbpedia_ent/dto/n1/a/trie_aq.py
dbpedia_ent/dto/n1/a/trie_ar.py
dbpedia_ent/dto/n1/a/trie_as.py
dbpedia_ent/dto/n1/a/trie_at.py
dbpedia_ent/dto/n1/a/trie_au.py
dbpedia_ent/dto/n1/a/trie_av.py
dbpedia_ent/dto/n1/a/trie_aw.py
dbpedia_ent/dto/n1/a/trie_ax.py
dbpedia_ent/dto/n1/a/trie_ay.py
dbpedia_ent/dto/n1/a/trie_az.py
dbpedia_ent/dto/n1/b/__init__.py
dbpedia_ent/dto/n1/b/finder_n1_b.py
dbpedia_ent/dto/n1/b/trie_b_.py
dbpedia_ent/dto/n1/b/trie_ba.py
dbpedia_ent/dto/n1/b/trie_bb.py
dbpedia_ent/dto/n1/b/trie_bc.py
dbpedia_ent/dto/n1/b/trie_bd.py
dbpedia_ent/dto/n1/b/trie_be.py
dbpedia_ent/dto/n1/b/trie_bf.py
dbpedia_ent/dto/n1/b/trie_bg.py
dbpedia_ent/dto/n1/b/trie_bh.py
dbpedia_ent/dto/n1/b/trie_bi.py
dbpedia_ent/dto/n1/b/trie_bj.py
dbpedia_ent/dto/n1/b/trie_bk.py
dbpedia_ent/dto/n1/b/trie_bl.py
dbpedia_ent/dto/n1/b/trie_bm.py
dbpedia_ent/dto/n1/b/trie_bn.py
dbpedia_ent/dto/n1/b/trie_bo.py
dbpedia_ent/dto/n1/b/trie_bp.py
dbpedia_ent/dto/n1/b/trie_bq.py
dbpedia_ent/dto/n1/b/trie_br.py
dbpedia_ent/dto/n1/b/trie_bs.py
dbpedia_ent/dto/n1/b/trie_bt.py
dbpedia_ent/dto/n1/b/trie_bu.py
dbpedia_ent/dto/n1/b/trie_bv.py
dbpedia_ent/dto/n1/b/trie_bw.py
dbpedia_ent/dto/n1/b/trie_bx.py
dbpedia_ent-0.1.4.dist-info/WHEEL
dbpedia_ent-0.1.4.dist-info/METADATA
dbpedia_ent-0.1.4.dist-info/RECORD
